pl_itn-0.1.0rc1.dist-info/METADATA
pl_itn-0.1.0rc1.dist-info/WHEEL
pl_itn-0.1.0rc1.dist-info/entry_points.txt
pl_itn-0.1.0rc1.dist-info/licenses/LICENSE
pl_itn/__init__.py
pl_itn/__main__.py
pl_itn/exceptions.py
pl_itn/grammars/__init__.py
pl_itn/grammars/tagger.fst
pl_itn/grammars/verbalizer.fst
pl_itn/logging.py
pl_itn/src/__init__.py
pl_itn/src/grammar.py
pl_itn/src/normalize.py
pl_itn/src/parse.py
pl_itn/src/permute.py
pl_itn/src/restore_uppercase.py
pl_itn/src/restore_whitespace.py
pl_itn/src/tag.py
pl_itn/src/utils.py
pl_itn/src/verbalize.py
pl_itn-0.1.0rc1.dist-info/RECORD
