Metadata-Version: 2.1
Name: pl-itn
Version: 0.1.0rc1
Summary: Polish FST Inverse Text Normalization
Keywords: fst itn text normalization polish
Author: mstopa, cansubmarinesswim
License: Apache-2.0
Classifier: Development Status :: 3 - Alpha
Classifier: Intended Audience :: Developers
Classifier: License :: OSI Approved :: Apache Software License
Classifier: Natural Language :: Polish
Classifier: Operating System :: POSIX :: Linux
Classifier: Programming Language :: Python :: 3.7
Classifier: Programming Language :: Python :: 3.8
Classifier: Programming Language :: Python :: 3.9
Classifier: Programming Language :: Python :: 3.10
Classifier: Programming Language :: Python :: 3.11
Classifier: Topic :: Text Processing
Project-URL: Repository, https://github.com/mstopa/pl_itn
Project-URL: Documentation, https://pl_itn.readthedocs.io/en/latest/
Requires-Python: >=3.7
Requires-Dist: pynini>=2.1.4
Requires-Dist: pyyaml>=6.0
